setup.py
SHICTHRSConfigLoader/__init__.py
SHICTHRSConfigLoader.egg-info/PKG-INFO
SHICTHRSConfigLoader.egg-info/SOURCES.txt
SHICTHRSConfigLoader.egg-info/dependency_links.txt
SHICTHRSConfigLoader.egg-info/not-zip-safe
SHICTHRSConfigLoader.egg-info/requires.txt
SHICTHRSConfigLoader.egg-info/top_level.txt
SHICTHRSConfigLoader/utils/SHRConfigLoader_readConfigFile.py
SHICTHRSConfigLoader/utils/SHRConfigLoader_readConfigFileBase.py
SHICTHRSConfigLoader/utils/SHRConfigLoader_writeConfigFile.py
SHICTHRSConfigLoader/utils/__init__.py