Metadata-Version: 2.4
Name: SHICTHRSConfigLoader
Version: 1.5.0
Summary: SHICTHRS Config file logging system
Home-page: https://github.com/JNTMTMTM/SHICTHRS_ConfigLoader
Author: SHICTHRS
Author-email: contact@shicthrs.com
License: GPL-3.0
Requires-Dist: colorama==0.4.6
Dynamic: author
Dynamic: author-email
Dynamic: home-page
Dynamic: license
Dynamic: requires-dist
Dynamic: summary
